mseep_sefaria_jewish_library-0.1.4.dist-info/licenses/LICENSE
sefaria_jewish_library/__init__.py
sefaria_jewish_library/demo.py
sefaria_jewish_library/sefaria_handler.py
sefaria_jewish_library/server.py
mseep_sefaria_jewish_library-0.1.4.dist-info/METADATA
mseep_sefaria_jewish_library-0.1.4.dist-info/WHEEL
mseep_sefaria_jewish_library-0.1.4.dist-info/entry_points.txt
mseep_sefaria_jewish_library-0.1.4.dist-info/top_level.txt
mseep_sefaria_jewish_library-0.1.4.dist-info/RECORD
