Metadata-Version: 2.4
Name: mseep-sefaria_jewish_library
Version: 0.1.4
Summary: the jewish library, accessible to LLMs 
Author-email: mseep <support@skydeck.ai>
Requires-Python: >=3.12
License-File: LICENSE
Requires-Dist: mcp>=1.3.0
Requires-Dist: requests
Dynamic: license-file
